LICENSE.txt
MANIFEST.in
README.md
setup.py
humilis_microservice/__init__.py
humilis_microservice/meta.yaml.j2
humilis_microservice/outputs.yaml.j2
humilis_microservice/plugin.py
humilis_microservice/resources.yaml.j2
humilis_microservice.egg-info/PKG-INFO
humilis_microservice.egg-info/SOURCES.txt
humilis_microservice.egg-info/dependency_links.txt
humilis_microservice.egg-info/entry_points.txt
humilis_microservice.egg-info/not-zip-safe
humilis_microservice.egg-info/requires.txt
humilis_microservice.egg-info/top_level.txt
humilis_microservice/lambda_function/__init__.py
humilis_microservice/lambda_function/setup.py
humilis_microservice/lambda_function/handler/__init__.py