Metadata-Version: 2.1
Name: humilis-microservice
Version: 0.5.0
Summary: Humilis plug-in to deploy a Lambda microservice
Home-page: https://github.com/humilis/humilis-microservice
Author: German Gomez-Herrero, FindHotel BV
Author-email: german@findhotel.net
License: MIT
Classifier: Programming Language :: Python :: 3
License-File: LICENSE.txt
